mounttree/__init__.py
mounttree/debug.py
mounttree/mounttree.py
mounttree-1.0.1.dist-info/licenses/LICENSE
test/__init__.py
test/test_mounttree.py
test/test_mounttree_io.py
mounttree-1.0.1.dist-info/METADATA
mounttree-1.0.1.dist-info/WHEEL
mounttree-1.0.1.dist-info/top_level.txt
mounttree-1.0.1.dist-info/RECORD
