Metadata-Version: 2.4
Name: mounttree
Version: 1.0.1
Summary: Transformations between related coordinate systems
Home-page: https://github.com/d70-t/mounttree_py
Author: Tobias Kölling
Author-email: tobias.koelling@physik.uni-muenchen.de
Classifier: Programming Language :: Python :: 3
Classifier: License :: OSI Approved :: MIT License
Classifier: Operating System :: OS Independent
Requires-Python: >=3
License-File: LICENSE
Requires-Dist: numpy
Requires-Dist: pyyaml
Dynamic: author
Dynamic: author-email
Dynamic: classifier
Dynamic: description
Dynamic: description-content-type
Dynamic: home-page
Dynamic: license-file
Dynamic: requires-dist
Dynamic: requires-python
Dynamic: summary
